restocks_client/__init__.py
restocks_client/client.py
restocks_client/exceptions.py
restocks_client/filters.py
restocks_client/product.py
restocks_client/utils/__init__.py
restocks_client/utils/defaults.py
restocks_client/utils/helpers.py
restocks_client/utils/proxy_handler.py
utils/__init__.py
utils/defaults.py
utils/helpers.py
utils/proxy_handler.py
restocks_api_wrapper-0.1.2.dist-info/LICENSE
restocks_api_wrapper-0.1.2.dist-info/METADATA
restocks_api_wrapper-0.1.2.dist-info/WHEEL
restocks_api_wrapper-0.1.2.dist-info/top_level.txt
restocks_api_wrapper-0.1.2.dist-info/RECORD
