Metadata-Version: 2.1
Name: restocks-api-wrapper
Version: 0.1.2
Summary: A unofficial Python wrapper for the Restocks.net API
Home-page: https://github.com/AkiLetschne/restocks_api_wrapper
Author: AkiLetschne
License: MIT
Classifier: Environment :: Web Environment
Classifier: Intended Audience :: Developers
Classifier: Programming Language :: Python :: 3
Classifier: Operating System :: Unix
Classifier: Operating System :: MacOS :: MacOS X
Classifier: Operating System :: Microsoft :: Windows
Requires-Python: >=3.11
License-File: LICENSE
Requires-Dist: requests
Requires-Dist: lxml
